config.py
conflict_resolver.py
main.py
sync_executor.py
sync_planner.py
commands/__init__.py
commands/cloud.py
commands/env.py
commands/inspect.py
commands/local.py
commands/sync.py
commands/sync_apply_enhanced.py
commands/sync_enhanced.py
zerodb_cli-1.0.0.dist-info/licenses/LICENSE
zerodb_cli-1.0.0.dist-info/METADATA
zerodb_cli-1.0.0.dist-info/WHEEL
zerodb_cli-1.0.0.dist-info/entry_points.txt
zerodb_cli-1.0.0.dist-info/top_level.txt
zerodb_cli-1.0.0.dist-info/RECORD
