Metadata-Version: 2.4
Name: zerodb-cli
Version: 1.0.0
Summary: ZeroDB Local CLI - Manage local ZeroDB environment and sync with cloud
Home-page: https://www.ainative.studio
Author: AINative Studio
Author-email: hello@ainative.studio
Project-URL: Homepage, https://www.ainative.studio
Project-URL: Documentation, https://docs.ainative.studio/zerodb-local
Keywords: zerodb,database,cli,vector-database,sync,ainative,AINative,ai-database,AI Database,AINative Database,vector-db,embeddings,semantic-search,postgres,postgresql,docker,docker-compose,cloud-sync,data-sync,database-cli,ai-native,ai-tools,machine-learning,ml-database
Classifier: Development Status :: 4 - Beta
Classifier: Intended Audience :: Developers
Classifier: Topic :: Software Development :: Libraries :: Python Modules
Classifier: Topic :: Database
Classifier: Topic :: Database :: Database Engines/Servers
Classifier: License :: OSI Approved :: MIT License
Classifier: Programming Language :: Python :: 3
Classifier: Programming Language :: Python :: 3.9
Classifier: Programming Language :: Python :: 3.10
Classifier: Programming Language :: Python :: 3.11
Classifier: Programming Language :: Python :: 3.12
Classifier: Environment :: Console
Classifier: Operating System :: OS Independent
Requires-Python: >=3.9
License-File: LICENSE
Requires-Dist: typer>=0.9.0
Requires-Dist: rich>=13.0.0
Requires-Dist: requests>=2.31.0
Requires-Dist: httpx>=0.24.0
Dynamic: author
Dynamic: author-email
Dynamic: classifier
Dynamic: description
Dynamic: description-content-type
Dynamic: home-page
Dynamic: keywords
Dynamic: license-file
Dynamic: project-url
Dynamic: requires-dist
Dynamic: requires-python
Dynamic: summary
